{
  "2025-10-04_23:00": {
    "color": "blue-light",
    "text": "system",
    "isGrouped": false,
    "groupIndex": 0,
    "groupLength": 1
  },
  "2025-10-04_23:30": {
    "color": "blue-light",
    "text": "",
    "isGrouped": true,
    "groupIndex": 1,
    "groupLength": 6
  },
  "2025-10-04_24:00": {
    "color": "blue-light",
    "text": "",
    "isGrouped": true,
    "groupIndex": 2,
    "groupLength": 6
  },
  "2025-10-04_24:30": {
    "color": "blue-light",
    "text": "",
    "isGrouped": true,
    "groupIndex": 3,
    "groupLength": 6
  },
  "2025-10-04_25:00": {
    "color": "blue-light",
    "text": "",
    "isGrouped": true,
    "groupIndex": 4,
    "groupLength": 6
  },
  "2025-10-04_25:30": {
    "color": "blue-light",
    "text": "",
    "isGrouped": true,
    "groupIndex": 5,
    "groupLength": 6
  },
  "2025-10-05_07:30": {
    "color": "blue-light",
    "text": "AP-test study",
    "isGrouped": true,
    "groupIndex": 0,
    "groupLength": 19
  },
  "2025-10-05_08:00": {
    "color": "blue-light",
    "text": "",
    "isGrouped": true,
    "groupIndex": 1,
    "groupLength": 19
  },
  "2025-10-05_08:30": {
    "color": "blue-light",
    "text": "",
    "isGrouped": true,
    "groupIndex": 2,
    "groupLength": 19
  },
  "2025-10-05_09:00": {
    "color": "blue-light",
    "text": "",
    "isGrouped": true,
    "groupIndex": 3,
    "groupLength": 19
  },
  "2025-10-05_09:30": {
    "color": "blue-light",
    "text": "",
    "isGrouped": true,
    "groupIndex": 4,
    "groupLength": 19
  },
  "2025-10-05_10:00": {
    "color": "blue-light",
    "text": "",
    "isGrouped": true,
    "groupIndex": 5,
    "groupLength": 19
  },
  "2025-10-05_10:30": {
    "color": "blue-light",
    "text": "",
    "isGrouped": true,
    "groupIndex": 6,
    "groupLength": 19
  },
  "2025-10-05_11:00": {
    "color": "blue-light",
    "text": "",
    "isGrouped": true,
    "groupIndex": 7,
    "groupLength": 19
  },
  "2025-10-05_11:30": {
    "color": "blue-light",
    "text": "",
    "isGrouped": true,
    "groupIndex": 8,
    "groupLength": 19
  },
  "2025-10-05_12:00": {
    "color": "blue-light",
    "text": "",
    "isGrouped": true,
    "groupIndex": 9,
    "groupLength": 19
  },
  "2025-10-05_12:30": {
    "color": "purple-light",
    "text": "home",
    "isGrouped": true,
    "groupIndex": 0,
    "groupLength": 3
  },
  "2025-10-05_13:00": {
    "color": "purple-light",
    "text": "",
    "isGrouped": true,
    "groupIndex": 1,
    "groupLength": 3
  },
  "2025-10-05_13:30": {
    "color": "purple-light",
    "text": "",
    "isGrouped": true,
    "groupIndex": 2,
    "groupLength": 3
  },
  "2025-10-05_14:00": {
    "color": "blue-light",
    "text": "",
    "isGrouped": true,
    "groupIndex": 13,
    "groupLength": 19
  },
  "2025-10-05_14:30": {
    "color": "blue-light",
    "text": "",
    "isGrouped": true,
    "groupIndex": 14,
    "groupLength": 19
  },
  "2025-10-05_15:00": {
    "color": "blue-light",
    "text": "",
    "isGrouped": true,
    "groupIndex": 15,
    "groupLength": 19
  },
  "2025-10-05_15:30": {
    "color": "blue-light",
    "text": "",
    "isGrouped": true,
    "groupIndex": 16,
    "groupLength": 19
  },
  "2025-10-05_16:00": {
    "color": "blue-light",
    "text": "",
    "isGrouped": true,
    "groupIndex": 17,
    "groupLength": 19
  },
  "2025-10-05_16:30": {
    "color": "blue-light",
    "text": "",
    "isGrouped": true,
    "groupIndex": 18,
    "groupLength": 19
  }
}